README.md
setup.py
neotasker/__init__.py
neotasker/embed.py
neotasker/f.py
neotasker/localproxy.py
neotasker/supervisor.py
neotasker/workers.py
neotasker.egg-info/PKG-INFO
neotasker.egg-info/SOURCES.txt
neotasker.egg-info/dependency_links.txt
neotasker.egg-info/requires.txt
neotasker.egg-info/top_level.txt