Metadata-Version: 2.1
Name: neotasker
Version: 0.0.39
Summary: Lightweight thread and asyncio task library
Home-page: https://github.com/alttch/neotasker
Author: Altertech
Author-email: div@altertech.com
License: MIT
Platform: UNKNOWN
Classifier: Programming Language :: Python :: 3
Classifier: License :: OSI Approved :: MIT License
Classifier: Topic :: Software Development :: Libraries
